LICENSE
MANIFEST.in
README.rst
VERSION
setup.py
ansigenome/__init__.py
ansigenome/color.py
ansigenome/config.py
ansigenome/constants.py
ansigenome/export.py
ansigenome/init.py
ansigenome/run.py
ansigenome/scan.py
ansigenome/test_helpers.py
ansigenome/ui.py
ansigenome/utils.py
ansigenome.egg-info/PKG-INFO
ansigenome.egg-info/SOURCES.txt
ansigenome.egg-info/dependency_links.txt
ansigenome.egg-info/pbr.json
ansigenome.egg-info/requires.txt
ansigenome.egg-info/top_level.txt
ansigenome/data/README.md.j2
ansigenome/data/README.rst.j2
ansigenome/data/colors
bin/ansigenome
docs/ansigenome-graph.png
docs/ansigenome-scan.png