Metadata-Version: 1.0
Name: ansigenome
Version: 0.5.5
Summary: A tool to help you gather information and manage your Ansible roles.
Home-page: https://github.com/nickjj/ansigenome
Author: Nick Janetakis
Author-email: nick.janetakis@gmail.com
License: GPLv3
Platform: UNKNOWN
